partitionpi/__init__.py
partitionpi/partition_graph.py
partitionpi/domain/__init__.py
partitionpi/domain/base.py
partitionpi/domain/math_utils.py
partitionpi/domain/methods.py
partitionpi/domain/operators.py
partitionpi-0.0.2.dist-info/LICENSE
partitionpi-0.0.2.dist-info/METADATA
partitionpi-0.0.2.dist-info/WHEEL
partitionpi-0.0.2.dist-info/top_level.txt
partitionpi-0.0.2.dist-info/RECORD
