Metadata-Version: 2.1
Name: partitionpi
Version: 0.0.2
Summary: Python library to handle integer partitions and compute partitional analysis metrics.
Home-page: https://github.com/luansimoes/partitionpi
Author: Luan Simões
Author-email: luansimoes@cos.ufrj.br
License: MIT License
Keywords: integer-partition texture music partitional analysis
Platform: UNKNOWN
Requires-Dist: networkx >=3
Requires-Dist: matplotlib >=3
